capella_ros_tools/.license_header.txt
capella_ros_tools/__init__.py
capella_ros_tools/__main__.py
capella_ros_tools/data_model.py
capella_ros_tools/exporter.py
capella_ros_tools/importer.py
capella_ros_tools-0.1.dev72.dist-info/licenses/LICENSES/Apache-2.0.txt
capella_ros_tools-0.1.dev72.dist-info/licenses/LICENSES/CC0-1.0.txt
capella_ros_tools-0.1.dev72.dist-info/METADATA
capella_ros_tools-0.1.dev72.dist-info/WHEEL
capella_ros_tools-0.1.dev72.dist-info/top_level.txt
capella_ros_tools-0.1.dev72.dist-info/RECORD
