Metadata-Version: 2.4
Name: capella-ros-tools
Version: 0.1.dev72
Summary: Tools for importing ROS .msg files into Capella data package and vice versa.
Author: DB InfraGO AG
License-Expression: Apache-2.0
Project-URL: Homepage, https://github.com/dbinfrago/capella-ros-tools
Project-URL: Documentation, https://dbinfrago.github.io/capella-ros-tools
Platform: any
Classifier: Development Status :: 1 - Planning
Classifier: Natural Language :: English
Classifier: Operating System :: OS Independent
Classifier: Programming Language :: Python :: 3 :: Only
Classifier: Programming Language :: Python :: 3.10
Classifier: Programming Language :: Python :: 3.11
Classifier: Programming Language :: Python :: 3.12
Classifier: Programming Language :: Python :: 3.13
Classifier: Typing :: Typed
Requires-Python: <3.14,>=3.10
License-File: LICENSES/Apache-2.0.txt
License-File: LICENSES/CC0-1.0.txt
Requires-Dist: capellambse<0.7,>=0.6.6
Requires-Dist: click
Dynamic: license-file
